crapy/__about__.py
crapy/__init__.py
crapy/__main__.py
crapy/py.typed
crapy/third_party.py
crapy-0.0.3.dist-info/METADATA
crapy-0.0.3.dist-info/WHEEL
crapy-0.0.3.dist-info/RECORD
